[{"domain": "zuimeizu.com", "expires": "\u5468\u4e00, 12 2\u6708 2018 18:17:30 GMT", "expiry": 1518459450, "httponly": false, "name": "mJaF_2132_lastact", "path": "/", "secure": false, "value": "1518373053%09misc.php%09patch"}, {"domain": "zuimeizu.com", "httponly": false, "name": "mJaF_2132_lip", "path": "/", "secure": false, "value": "116.23.155.37%2C1518373053"}, {"domain": "zuimeizu.com", "expires": "\u5468\u4e00, 12 2\u6708 2018 18:17:30 GMT", "expiry": 1518459450, "httponly": false, "name": "mJaF_2132_sid", "path": "/", "secure": false, "value": "uydzDp"}, {"domain": "zuimeizu.com", "expires": "\u5468\u65e5, 12 8\u6708 2018 18:17:30 GMT", "expiry": 1534097850, "httponly": false, "name": "CNZZDATA3389048", "path": "/", "secure": false, "value": "cnzz_eid%3D2134137984-1518340221-%26ntime%3D1518370849"}, {"domain": ".zuimeizu.com", "httponly": false, "name": "mJaF_2132_lastact", "path": "/", "secure": false, "value": "1518371190%09misc.php%09patch"}, {"domain": ".zuimeizu.com", "httponly": false, "name": "mJaF_2132_lip", "path": "/", "secure": false, "value": "47.91.196.168%2C1518371187"}, {"domain": ".zuimeizu.com", "httponly": false, "name": "CNZZDATA3389048", "path": "/", "secure": false, "value": "cnzz_eid%3D2134137984-1518340221-%26ntime%3D1518370849"}, {"domain": ".zuimeizu.com", "httponly": false, "name": "mJaF_2132_nofavfid", "path": "/", "secure": false, "value": "1"}, {"domain": ".zuimeizu.com", "httponly": false, "name": "mJaF_2132_ulastactivity", "path": "/", "secure": false, "value": "800eDC3ONuhZTPG2vLnkNYn219XDmo%2FOzRE%2FaN7YqiCZWznZ27Jz"}, {"domain": ".zuimeizu.com", "httponly": false, "name": "mJaF_2132_checkpm", "path": "/", "secure": false, "value": "1"}, {"domain": ".zuimeizu.com", "httponly": false, "name": "mJaF_2132_checkfollow", "path": "/", "secure": false, "value": "1"}, {"domain": ".zuimeizu.com", "httponly": false, "name": "mJaF_2132_auth", "path": "/", "secure": false, "value": "5358htAA85GJL8quwKefPqpThjLQmmF1f2aG7znTUOpKslS7aLOvmPEd9Lm96yK9jZi0tRwAZiEc6%2Fn0wQixxALYxQ"}, {"domain": ".zuimeizu.com", "httponly": false, "name": "mJaF_2132_sid", "path": "/", "secure": false, "value": "R6Kcvo"}, {"domain": ".zuimeizu.com", "httponly": false, "name": "mJaF_2132_lastcheckfeed", "path": "/", "secure": false, "value": "15836%7C1518344166"}, {"domain": ".zuimeizu.com", "httponly": false, "name": "CNZZDATA1266840871", "path": "/", "secure": false, "value": "903637265-1518343545-%7C1518343545"}, {"domain": ".zuimeizu.com", "httponly": false, "name": "101701|300|250|19|1|1|", "path": "/", "secure": false, "value": "101701%7C300%7C250%7C19%7C1%7C1%7C"}, {"domain": ".zuimeizu.com", "httponly": false, "name": "UM_distinctid", "path": "/", "secure": false, "value": "161845d05e0380-0d259e19e29e1a-70143942-1fa400-161845d05e1360"}, {"domain": ".zuimeizu.com", "httponly": false, "name": "mJaF_2132_sendmail", "path": "/", "secure": false, "value": "1"}, {"domain": ".zuimeizu.com", "httponly": false, "name": "mJaF_2132_lastvisit", "path": "/", "secure": false, "value": "1518340544"}, {"domain": ".zuimeizu.com", "httponly": false, "name": "mJaF_2132_saltkey", "path": "/", "secure": false, "value": "P0ESqYLl"}]